ai_lib/__init__.py
ai_lib/ai_lib.py
robotframework_roboai-0.2.2.dist-info/licenses/LICENSE
robotframework_roboai-0.2.2.dist-info/METADATA
robotframework_roboai-0.2.2.dist-info/WHEEL
robotframework_roboai-0.2.2.dist-info/entry_points.txt
robotframework_roboai-0.2.2.dist-info/top_level.txt
robotframework_roboai-0.2.2.dist-info/RECORD
